test_pkg_poetry_binlecode/__init__.py
test_pkg_poetry_binlecode/my_module.py
test_pkg_poetry_binlecode-0.1.5.dist-info/WHEEL
test_pkg_poetry_binlecode-0.1.5.dist-info/METADATA
test_pkg_poetry_binlecode-0.1.5.dist-info/RECORD
