Metadata-Version: 2.1
Name: test-pkg-poetry-binlecode
Version: 0.1.5
Summary: 
Home-page: https://github.com/binlecode/example-python-poetry
License: MIT
Author: Bin Le
Author-email: bin.le.code@gmail.com
Requires-Python: >=3.8,<4.0
Classifier: License :: OSI Approved :: MIT License
Classifier: Programming Language :: Python :: 3
Classifier: Programming Language :: Python :: 3.8
Classifier: Programming Language :: Python :: 3.9
Classifier: Programming Language :: Python :: 3.10
Classifier: Programming Language :: Python :: 3.11
Project-URL: Repository, https://github.com/binlecode/example-python-poetry
